Workbook

Sheet Objective & Guide
B2: B2B Session Drop Tracker — Germany (Amazon.de)
B4: SOURCE DATA
B5: Built from Amazon Seller Central Business Reports (Detail Page Sales and Traffic by Child Item) for Amazon.de, exported for two matching 30-day windows: 'Last 30 Days' and 'Previous 30 Days'. Uses B2B-specific columns only — Sessions – Total – B2B, Page Views – Total – B2B, Units ordered – B2B — not the blended B2B+B2C totals. Only ASINs with some B2B Sessions or B2B Page Views in either window are included; ASINs with zero B2B traffic both cycles are excluded, since there's no B2B signal to act on.
B7: OBJECTIVE
B8: Catch ASINs whose B2B (business customer) traffic dropped between the two 30-day windows, so a real decline in visibility to business buyers gets caught and investigated — instead of relying on B2B Conversion %, which was unreliable here because per-ASIN B2B session volume is too low for a percentage to mean much.
B11: HOW EACH COLUMN IS USED
B12: B2B Sessions (Prev / Current)
B13: Unique B2B visitor sessions to the product page, from Sessions – Total – B2B, for each 30-day window.
B14: B2B Page Views (Prev / Current)
B15: B2B page views, from Page Views – Total – B2B. Extra context alongside Sessions.
B16: B2B Unit Orders (Prev / Current)
B17: Units ordered by B2B customers only, from Units ordered – B2B — shown for context, not used to gate Status.
... B26: Two thresholds on the 'Thresholds' tab control the Tracker: the Tier 2 and Tier 3 session boundaries. These decide which Tier every ASIN falls into, and therefore which action text it gets. Change either value and the whole list recalculates automatically.

Sheet Thresholds
B2: Threshold Settings
B4: Tier | C4: B2B Sessions | D4: Action
B5: Tier 1 - Low | C5: ="< "&C6 -> < 5 | D5: Low/no B2B traffic yet - set a Business Price (5-10% below retail) and Quantity Discount tiers (e.g. 5+ units 5% off, 10+ units 10% off) to attract first B2B interest; add bulk/case-pack info to title and bullets
B6: Tier 2 - Moderate | C6: 5 | D6: Light check - Buy Box %, confirm Business Price/Quantity Discount still active, quick scan of title and main image
B7: Tier 3 - High | C7: 10 | D7: Priority review - Buy Box % and stock, Business Price and Quantity Discount tiers, spec table plus bulk/case-pack info, A+ business use-case content, Business-only offers enabled, VAT invoicing support, backend B2B search terms, certifications visible
B9: Blue cells (Tier 2 / Tier 3 'B2B Sessions') = editable inputs — the number entered is the lower bound of that tier. Tier 1's range updates automatically. Changing either blue cell updates every ASIN's Tier, Status, and Action on the Tracker tab automatically.

Sheet Tracker
A3: ASIN | B3: Prev B2B Sessions | C3: Prev B2B Page Views | D3: Prev B2B Orders | E3: Current B2B Sessions | F3: Current B2B Page Views | G3: Current B2B Orders | H3: Buy Box % (Current) | I3: Session Change | J3: Tier | K3: Status | L3: Action
A4: B0DLWRP73C | B4: 15 | C4: 21 | D4: 0 | E4: 4 | F4: 4 | G4: 0 | H4: 1 | I4: =E4-B4 -> -11 | J4: =IF(MAX(B4,E4)>=Thresholds!$C$7,"Tier 3 - High",IF(MAX(B4,E4)>=Thresholds!$C$6,"Tier 2 - Moderate","Tier 1 - Low")) -> Tier 3 - High | K4: =IF(J4="Tier 1 - Low","Low Volume - Setup Needed",IF(J4="Tier 2 - Moderate","Moderate - Review","High - Priority Review")) -> High - Priority Review | L4: =IF(J4="Tier 1 - Low","Low/no B2B traffic yet - set a Business Price (5-10% below retail) and Quantity Discount tiers (e.g. 5+ units 5% off, 10+ units 10% off) to attract first B2B interest; add bulk/case-pack info to title and bullets",IF(J4="Tier 2 - Moderate","Light check - Buy Box %, confirm Business Price/Quantity Discount still active, quick scan of title and main image","Priority review - Buy Box % and stock, Business Price and Quantity Discount tiers, spec table plus bulk/case-pack info, A+ business use-case content, Business-only offers enabled, VAT invoicing support, backend B2B search terms, certifications visible")) -> Priority review - Buy Box % and stock, Business Price and Quantity Discount tiers, spec table plus bulk/case-pack info, A+ business use-case content, Business-only offers enabled, VAT invoicing support, backend B2B search terms, certifications visible
A5: B0CGRNLLPR | B5: 10 | C5: 16 | D5: 5 | E5: 1 | F5: 1 | G5: 0 | H5: 0.0417 | I5: =E5-B5 -> -9 | J5: =IF(MAX(B5,E5)>=Thresholds!$C$7,"Tier 3 - High",IF(MAX(B5,E5)>=Thresholds!$C$6,"Tier 2 - Moderate","Tier 1 - Low")) -> Tier 3 - High | K5: =IF(J5="Tier 1 - Low","Low Volume - Setup Needed",IF(J5="Tier 2 - Moderate","Moderate - Review","High - Priority Review")) -> High - Priority Review | L5: =IF(J5="Tier 1 - Low","Low/no B2B traffic yet - set a Business Price (5-10% below retail) and Quantity Discount tiers (e.g. 5+ units 5% off, 10+ units 10% off) to attract first B2B interest; add bulk/case-pack info to title and bullets",IF(J5="Tier 2 - Moderate","Light check - Buy Box %, confirm Business Price/Quantity Discount still active, quick scan of title and main image","Priority review - Buy Box % and stock, Business Price and Quantity Discount tiers, spec table plus bulk/case-pack info, A+ business use-case content, Business-only offers enabled, VAT invoicing support, backend B2B search terms, certifications visible")) -> Priority review - Buy Box % and stock, Business Price and Quantity Discount tiers, spec table plus bulk/case-pack info, A+ business use-case content, Business-only offers enabled, VAT invoicing support, backend B2B search terms, certifications visible
A6: B0B2F3FLSL | B6: 7 | C6: 8 | D6: 3 | E6: 0 | F6: 0 | G6: 0 | H6: 0 | I6: =E6-B6 -> -7 | J6: =IF(MAX(B6,E6)>=Thresholds!$C$7,"Tier 3 - High",IF(MAX(B6,E6)>=Thresholds!$C$6,"Tier 2 - Moderate","Tier 1 - Low")) -> Tier 2 - Moderate | K6: =IF(J6="Tier 1 - Low","Low Volume - Setup Needed",IF(J6="Tier 2 - Moderate","Moderate - Review","High - Priority Review")) -> Moderate - Review | L6: =IF(J6="Tier 1 - Low","Low/no B2B traffic yet - set a Business Price (5-10% below retail) and Quantity Discount tiers (e.g. 5+ units 5% off, 10+ units 10% off) to attract first B2B interest; add bulk/case-pack info to title and bullets",IF(J6="Tier 2 - Moderate","Light check - Buy Box %, confirm Business Price/Quantity Discount still active, quick scan of title and main image","Priority review - Buy Box % and stock, Business Price and Quantity Discount tiers, spec table plus bulk/case-pack info, A+ business use-case content, Business-only offers enabled, VAT invoicing support, backend B2B search terms, certifications visible")) -> Light check - Buy Box %, confirm Business Price/Quantity Discount still active, quick scan of title and main image
A7: B0DYV8RX71 | B7: 15 | C7: 19 | D7: 0 | E7: 8 | F7: 14 | G7: 0 | H7: 1 | I7: =E7-B7 -> -7 | J7: =IF(MAX(B7,E7)>=Thresholds!$C$7,"Tier 3 - High",IF(MAX(B7,E7)>=Thresholds!$C$6,"Tier 2 - Moderate","Tier 1 - Low")) -> Tier 3 - High | K7: =IF(J7="Tier 1 - Low","Low Volume - Setup Needed",IF(J7="Tier 2 - Moderate","Moderate - Review","High - Priority Review")) -> High - Priority Review | L7: =IF(J7="Tier 1 - Low","Low/no B2B traffic yet - set a Business Price (5-10% below retail) and Quantity Discount tiers (e.g. 5+ units 5% off, 10+ units 10% off) to attract first B2B interest; add bulk/case-pack info to title and bullets",IF(J7="Tier 2 - Moderate","Light check - Buy Box %, confirm Business Price/Quantity Discount still active, quick scan of title and main image","Priority review - Buy Box % and stock, Business Price and Quantity Discount tiers, spec table plus bulk/case-pack info, A+ business use-case content, Business-only offers enabled, VAT invoicing support, backend B2B search terms, certifications visible")) -> Priority review - Buy Box % and stock, Business Price and Quantity Discount tiers, spec table plus bulk/case-pack info, A+ business use-case content, Business-only offers enabled, VAT invoicing support, backend B2B search terms, certifications visible
A8: B09C5SYCR3 | B8: 7 | C8: 7 | D8: 0 | E8: 0 | F8: 0 | G8: 0 | H8: 1 | I8: =E8-B8 -> -7 | J8: =IF(MAX(B8,E8)>=Thresholds!$C$7,"Tier 3 - High",IF(MAX(B8,E8)>=Thresholds!$C$6,"Tier 2 - Moderate","Tier 1 - Low")) -> Tier 2 - Moderate | K8: =IF(J8="Tier 1 - Low","Low Volume - Setup Needed",IF(J8="Tier 2 - Moderate","Moderate - Review","High - Priority Review")) -> Moderate - Review | L8: =IF(J8="Tier 1 - Low","Low/no B2B traffic yet - set a Business Price (5-10% below retail) and Quantity Discount tiers (e.g. 5+ units 5% off, 10+ units 10% off) to attract first B2B interest; add bulk/case-pack info to title and bullets",IF(J8="Tier 2 - Moderate","Light check - Buy Box %, confirm Business Price/Quantity Discount still active, quick scan of title and main image","Priority review - Buy Box % and stock, Business Price and Quantity Discount tiers, spec table plus bulk/case-pack info, A+ business use-case content, Business-only offers enabled, VAT invoicing support, backend B2B search terms, certifications visible")) -> Light check - Buy Box %, confirm Business Price/Quantity Discount still active, quick scan of title and main image
A9: B09LMKNDW7 | B9: 9 | C9: 29 | D9: 0 | E9: 2 | F9: 2 | G9: 0 | H9: 1 | I9: =E9-B9 -> -7 | J9: =IF(MAX(B9,E9)>=Thresholds!$C$7,"Tier 3 - High",IF(MAX(B9,E9)>=Thresholds!$C$6,"Tier 2 - Moderate","Tier 1 - Low")) -> Tier 2 - Moderate | K9: =IF(J9="Tier 1 - Low","Low Volume - Setup Needed",IF(J9="Tier 2 - Moderate","Moderate - Review","High - Priority Review")) -> Moderate - Review | L9: =IF(J9="Tier 1 - Low","Low/no B2B traffic yet - set a Business Price (5-10% below retail) and Quantity Discount tiers (e.g. 5+ units 5% off, 10+ units 10% off) to attract first B2B interest; add bulk/case-pack info to title and bullets",IF(J9="Tier 2 - Moderate","Light check - Buy Box %, confirm Business Price/Quantity Discount still active, quick scan of title and main image","Priority review - Buy Box % and stock, Business Price and Quantity Discount tiers, spec table plus bulk/case-pack info, A+ business use-case content, Business-only offers enabled, VAT invoicing support, backend B2B search terms, certifications visible")) -> Light check - Buy Box %, confirm Business Price/Quantity Discount still active, quick scan of title and main image
A10: B084FXGQZ7 | B10: 7 | C10: 19 | D10: 2 | E10: 0 | F10: 0 | G10: 0 | H10: 0.6154 | I10: =E10-B10 -> -7 | J10: =IF(MAX(B10,E10)>=Thresholds!$C$7,"Tier 3 - High",IF(MAX(B10,E10)>=Thresholds!$C$6,"Tier 2 - Moderate","Tier 1 - Low")) -> Tier 2 - Moderate | K10: =IF(J10="Tier 1 - Low","Low Volume - Setup Needed",IF(J10="Tier 2 - Moderate","Moderate - Review","High - Priority Review")) -> Moderate - Review | L10: =IF(J10="Tier 1 - Low","Low/no B2B traffic yet - set a Business Price (5-10% below retail) and Quantity Discount tiers (e.g. 5+ units 5% off, 10+ units 10% off) to attract first B2B interest; add bulk/case-pack info to title and bullets",IF(J10="Tier 2 - Moderate","Light check - Buy Box %, confirm Business Price/Quantity Discount still active, quick scan of title and main image","Priority review - Buy Box % and stock, Business Price and Quantity Discount tiers, spec table plus bulk/case-pack info, A+ business use-case content, Business-only offers enabled, VAT invoicing support, backend B2B search terms, certifications visible")) -> Light check - Buy Box %, confirm Business Price/Quantity Discount still active, quick scan of title and main image
A11: B0DQD74HVG | B11: 7 | C11: 10 | D11: 0 | E11: 1 | F11: 1 | G11: 0 | H11: 0.9375 | I11: =E11-B11 -> -6 | J11: =IF(MAX(B11,E11)>=Thresholds!$C$7,"Tier 3 - High",IF(MAX(B11,E11)>=Thresholds!$C$6,"Tier 2 - Moderate","Tier 1 - Low")) -> Tier 2 - Moderate | K11: =IF(J11="Tier 1 - Low","Low Volume - Setup Needed",IF(J11="Tier 2 - Moderate","Moderate - Review","High - Priority Review")) -> Moderate - Review | L11: =IF(J11="Tier 1 - Low","Low/no B2B traffic yet - set a Business Price (5-10% below retail) and Quantity Discount tiers (e.g. 5+ units 5% off, 10+ units 10% off) to attract first B2B interest; add bulk/case-pack info to title and bullets",IF(J11="Tier 2 - Moderate","Light check - Buy Box %, confirm Business Price/Quantity Discount still active, quick scan of title and main image","Priority review - Buy Box % and stock, Business Price and Quantity Discount tiers, spec table plus bulk/case-pack info, A+ business use-case content, Business-only offers enabled, VAT invoicing support, backend B2B search terms, certifications visible")) -> Light check - Buy Box %, confirm Business Price/Quantity Discount still active, quick scan of title and main image
A12: B0D8P6VR32 | B12: 6 | C12: 8 | D12: 0 | E12: 0 | F12: 0 | G12: 0 | H12: 0 | I12: =E12-B12 -> -6 | J12: =IF(MAX(B12,E12)>=Thresholds!$C$7,"Tier 3 - High",IF(MAX(B12,E12)>=Thresholds!$C$6,"Tier 2 - Moderate","Tier 1 - Low")) -> Tier 2 - Moderate | K12: =IF(J12="Tier 1 - Low","Low Volume - Setup Needed",IF(J12="Tier 2 - Moderate","Moderate - Review","High - Priority Review")) -> Moderate - Review | L12: =IF(J12="Tier 1 - Low","Low/no B2B traffic yet - set a Business Price (5-10% below retail) and Quantity Discount tiers (e.g. 5+ units 5% off, 10+ units 10% off) to attract first B2B interest; add bulk/case-pack info to title and bullets",IF(J12="Tier 2 - Moderate","Light check - Buy Box %, confirm Business Price/Quantity Discount still active, quick scan of title and main image","Priority review - Buy Box % and stock, Business Price and Quantity Discount tiers, spec table plus bulk/case-pack info, A+ business use-case content, Business-only offers enabled, VAT invoicing support, backend B2B search terms, certifications visible")) -> Light check - Buy Box %, confirm Business Price/Quantity Discount still active, quick scan of title and main image
A13: B0DLWST7KG | B13: 5 | C13: 11 | D13: 1 | E13: 0 | F13: 0 | G13: 0 | H13: 0.9515 | I13: =E13-B13 -> -5 | J13: =IF(MAX(B13,E13)>=Thresholds!$C$7,"Tier 3 - High",IF(MAX(B13,E13)>=Thresholds!$C$6,"Tier 2 - Moderate","Tier 1 - Low")) -> Tier 2 - Moderate | K13: =IF(J13="Tier 1 - Low","Low Volume - Setup Needed",IF(J13="Tier 2 - Moderate","Moderate - Review","High - Priority Review")) -> Moderate - Review | L13: =IF(J13="Tier 1 - Low","Low/no B2B traffic yet - set a Business Price (5-10% below retail) and Quantity Discount tiers (e.g. 5+ units 5% off, 10+ units 10% off) to attract first B2B interest; add bulk/case-pack info to title and bullets",IF(J13="Tier 2 - Moderate","Light check - Buy Box %, confirm Business Price/Quantity Discount still active, quick scan of title and main image","Priority review - Buy Box % and stock, Business Price and Quantity Discount tiers, spec table plus bulk/case-pack info, A+ business use-case content, Business-only offers enabled, VAT invoicing support, backend B2B search terms, certifications visible")) -> Light check - Buy Box %, confirm Business Price/Quantity Discount still active, quick scan of title and main image
A14: B0DM221HWB | B14: 5 | C14: 7 | D14: 0 | E14: 0 | F14: 0 | G14: 0 | H14: 1 | I14: =E14-B14 -> -5 | J14: =IF(MAX(B14,E14)>=Thresholds!$C$7,"Tier 3 - High",IF(MAX(B14,E14)>=Thresholds!$C$6,"Tier 2 - Moderate","Tier 1 - Low")) -> Tier 2 - Moderate | K14: =IF(J14="Tier 1 - Low","Low Volume - Setup Needed",IF(J14="Tier 2 - Moderate","Moderate - Review","High - Priority Review")) -> Moderate - Review | L14: =IF(J14="Tier 1 - Low","Low/no B2B traffic yet - set a Business Price (5-10% below retail) and Quantity Discount tiers (e.g. 5+ units 5% off, 10+ units 10% off) to attract first B2B interest; add bulk/case-pack info to title and bullets",IF(J14="Tier 2 - Moderate","Light check - Buy Box %, confirm Business Price/Quantity Discount still active, quick scan of title and main image","Priority review - Buy Box % and stock, Business Price and Quantity Discount tiers, spec table plus bulk/case-pack info, A+ business use-case content, Business-only offers enabled, VAT invoicing support, backend B2B search terms, certifications visible")) -> Light check - Buy Box %, confirm Business Price/Quantity Discount still active, quick scan of title and main image
A15: B0CZXSKPGY | B15: 4 | C15: 6 | D15: 0 | E15: 0 | F15: 0 | G15: 0 | H15: 0.3333 | I15: =E15-B15 -> -4 | J15: =IF(MAX(B15,E15)>=Thresholds!$C$7,"Tier 3 - High",IF(MAX(B15,E15)>=Thresholds!$C$6,"Tier 2 - Moderate","Tier 1 - Low")) -> Tier 1 - Low | K15: =IF(J15="Tier 1 - Low","Low Volume - Setup Needed",IF(J15="Tier 2 - Moderate","Moderate - Review","High - Priority Review")) -> Low Volume - Setup Needed | L15: =IF(J15="Tier 1 - Low","Low/no B2B traffic yet - set a Business Price (5-10% below retail) and Quantity Discount tiers (e.g. 5+ units 5% off, 10+ units 10% off) to attract first B2B interest; add bulk/case-pack info to title and bullets",IF(J15="Tier 2 - Moderate","Light check - Buy Box %, confirm Business Price/Quantity Discount still active, quick scan of title and main image","Priority review - Buy Box % and stock, Business Price and Quantity Discount tiers, spec table plus bulk/case-pack info, A+ business use-case content, Business-only offers enabled, VAT invoicing support, backend B2B search terms, certifications visible")) -> Low/no B2B traffic yet - set a Business Price (5-10% below retail) and Quantity Discount tiers (e.g. 5+ units 5% off, 10+ units 10% off) to attract first B2B interest; add bulk/case-pack info to title and bullets
... A529: B0CBMH92KR | B529: 3 | C529: 4 | D529: 0 | E529: 8 | F529: 16 | G529: 0 | H529: 0.8108 | I529: =E529-B529 -> 5 | J529: =IF(MAX(B529,E529)>=Thresholds!$C$7,"Tier 3 - High",IF(MAX(B529,E529)>=Thresholds!$C$6,"Tier 2 - Moderate","Tier 1 - Low")) -> Tier 2 - Moderate | K529: =IF(J529="Tier 1 - Low","Low Volume - Setup Needed",IF(J529="Tier 2 - Moderate","Moderate - Review","High - Priority Review")) -> Moderate - Review | L529: =IF(J529="Tier 1 - Low","Low/no B2B traffic yet - set a Business Price (5-10% below retail) and Quantity Discount tiers (e.g. 5+ units 5% off, 10+ units 10% off) to attract first B2B interest; add bulk/case-pack info to title and bullets",IF(J529="Tier 2 - Moderate","Light check - Buy Box %, confirm Business Price/Quantity Discount still active, quick scan of title and main image","Priority review - Buy Box % and stock, Business Price and Quantity Discount tiers, spec table plus bulk/case-pack info, A+ business use-case content, Business-only offers enabled, VAT invoicing support, backend B2B search terms, certifications visible")) -> Light check - Buy Box %, confirm Business Price/Quantity Discount still active, quick scan of title and main image
