Workbook

Sheet Tracker
A1: B2B Session Drop Tracker — Amazon.de (Germany) · End user: Jensika (staff.users id 99)
A2: Current: 16 Jun 2026 – 15 Jul 2026 | Previous: 17 May 2026 – 15 Jun 2026 | Tier by MAX(prev,current) B2B Sessions (Tier 2 ≥ 5, Tier 3 ≥ 10) | 526 ASINs
A3: ASIN | B3: Prev B2B Sessions | C3: Prev B2B Page Views | D3: Prev B2B Orders | E3: Current B2B Sessions | F3: Current B2B Page Views | G3: Current B2B Orders | H3: Buy Box % (Current) | I3: Session Change | J3: Tier | K3: Status | L3: Action
A4: B0DLWRP73C | B4: 15 | C4: 21 | D4: 0 | E4: 4 | F4: 4 | G4: 0 | H4: 1 | I4: =E4-B4 | J4: =IF(MAX(B4,E4)>=Thresholds!$B$5,"Tier 3 - High",IF(MAX(B4,E4)>=Thresholds!$B$4,"Tier 2 - Moderate","Tier 1 - Low")) | K4: High - Priority Review | L4: Priority review - Buy Box % and stock, Business Price and Quantity Discount tiers, spec table plus bulk/case-pack info, A+ business use-case content, Business-only offers enabled, VAT invoicing support, backend B2B search terms, certifications visible
A5: B0CGRNLLPR | B5: 10 | C5: 16 | D5: 5 | E5: 1 | F5: 1 | G5: 0 | H5: 0.0417 | I5: =E5-B5 | J5: =IF(MAX(B5,E5)>=Thresholds!$B$5,"Tier 3 - High",IF(MAX(B5,E5)>=Thresholds!$B$4,"Tier 2 - Moderate","Tier 1 - Low")) | K5: High - Priority Review | L5: Priority review - Buy Box % and stock, Business Price and Quantity Discount tiers, spec table plus bulk/case-pack info, A+ business use-case content, Business-only offers enabled, VAT invoicing support, backend B2B search terms, certifications visible
A6: B0B2F3FLSL | B6: 7 | C6: 8 | D6: 3 | E6: 0 | F6: 0 | G6: 0 | H6: 0 | I6: =E6-B6 | J6: =IF(MAX(B6,E6)>=Thresholds!$B$5,"Tier 3 - High",IF(MAX(B6,E6)>=Thresholds!$B$4,"Tier 2 - Moderate","Tier 1 - Low")) | K6: Moderate - Review | L6: Light check - Buy Box %, confirm Business Price/Quantity Discount still active, quick scan of title and main image
A7: B0DYV8RX71 | B7: 15 | C7: 19 | D7: 0 | E7: 8 | F7: 14 | G7: 0 | H7: 1 | I7: =E7-B7 | J7: =IF(MAX(B7,E7)>=Thresholds!$B$5,"Tier 3 - High",IF(MAX(B7,E7)>=Thresholds!$B$4,"Tier 2 - Moderate","Tier 1 - Low")) | K7: High - Priority Review | L7: Priority review - Buy Box % and stock, Business Price and Quantity Discount tiers, spec table plus bulk/case-pack info, A+ business use-case content, Business-only offers enabled, VAT invoicing support, backend B2B search terms, certifications visible
A8: B09C5SYCR3 | B8: 7 | C8: 7 | D8: 0 | E8: 0 | F8: 0 | G8: 0 | H8: 1 | I8: =E8-B8 | J8: =IF(MAX(B8,E8)>=Thresholds!$B$5,"Tier 3 - High",IF(MAX(B8,E8)>=Thresholds!$B$4,"Tier 2 - Moderate","Tier 1 - Low")) | K8: Moderate - Review | L8: Light check - Buy Box %, confirm Business Price/Quantity Discount still active, quick scan of title and main image
A9: B09LMKNDW7 | B9: 9 | C9: 29 | D9: 0 | E9: 2 | F9: 2 | G9: 0 | H9: 1 | I9: =E9-B9 | J9: =IF(MAX(B9,E9)>=Thresholds!$B$5,"Tier 3 - High",IF(MAX(B9,E9)>=Thresholds!$B$4,"Tier 2 - Moderate","Tier 1 - Low")) | K9: Moderate - Review | L9: Light check - Buy Box %, confirm Business Price/Quantity Discount still active, quick scan of title and main image
A10: B084FXGQZ7 | B10: 7 | C10: 19 | D10: 2 | E10: 0 | F10: 0 | G10: 0 | H10: 0.6154 | I10: =E10-B10 | J10: =IF(MAX(B10,E10)>=Thresholds!$B$5,"Tier 3 - High",IF(MAX(B10,E10)>=Thresholds!$B$4,"Tier 2 - Moderate","Tier 1 - Low")) | K10: Moderate - Review | L10: Light check - Buy Box %, confirm Business Price/Quantity Discount still active, quick scan of title and main image
A11: B0DQD74HVG | B11: 7 | C11: 10 | D11: 0 | E11: 1 | F11: 1 | G11: 0 | H11: 0.9375 | I11: =E11-B11 | J11: =IF(MAX(B11,E11)>=Thresholds!$B$5,"Tier 3 - High",IF(MAX(B11,E11)>=Thresholds!$B$4,"Tier 2 - Moderate","Tier 1 - Low")) | K11: Moderate - Review | L11: Light check - Buy Box %, confirm Business Price/Quantity Discount still active, quick scan of title and main image
A12: B0D8P6VR32 | B12: 6 | C12: 8 | D12: 0 | E12: 0 | F12: 0 | G12: 0 | H12: 0 | I12: =E12-B12 | J12: =IF(MAX(B12,E12)>=Thresholds!$B$5,"Tier 3 - High",IF(MAX(B12,E12)>=Thresholds!$B$4,"Tier 2 - Moderate","Tier 1 - Low")) | K12: Moderate - Review | L12: Light check - Buy Box %, confirm Business Price/Quantity Discount still active, quick scan of title and main image
A13: B0DLWST7KG | B13: 5 | C13: 11 | D13: 1 | E13: 0 | F13: 0 | G13: 0 | H13: 0.9515 | I13: =E13-B13 | J13: =IF(MAX(B13,E13)>=Thresholds!$B$5,"Tier 3 - High",IF(MAX(B13,E13)>=Thresholds!$B$4,"Tier 2 - Moderate","Tier 1 - Low")) | K13: Moderate - Review | L13: Light check - Buy Box %, confirm Business Price/Quantity Discount still active, quick scan of title and main image
A14: B0DM221HWB | B14: 5 | C14: 7 | D14: 0 | E14: 0 | F14: 0 | G14: 0 | H14: 1 | I14: =E14-B14 | J14: =IF(MAX(B14,E14)>=Thresholds!$B$5,"Tier 3 - High",IF(MAX(B14,E14)>=Thresholds!$B$4,"Tier 2 - Moderate","Tier 1 - Low")) | K14: Moderate - Review | L14: Light check - Buy Box %, confirm Business Price/Quantity Discount still active, quick scan of title and main image
A15: B0CZXSKPGY | B15: 4 | C15: 6 | D15: 0 | E15: 0 | F15: 0 | G15: 0 | H15: 0.3333 | I15: =E15-B15 | J15: =IF(MAX(B15,E15)>=Thresholds!$B$5,"Tier 3 - High",IF(MAX(B15,E15)>=Thresholds!$B$4,"Tier 2 - Moderate","Tier 1 - Low")) | K15: Low Volume - Setup Needed | L15: Low/no B2B traffic yet - set a Business Price (5-10% below retail) and Quantity Discount tiers (e.g. 5+ units 5% off, 10+ units 10% off) to attract first B2B interest; add bulk/case-pack info to title and bullets
... A529: B0CBMH92KR | B529: 3 | C529: 4 | D529: 0 | E529: 8 | F529: 16 | G529: 0 | H529: 0.8108 | I529: =E529-B529 | J529: =IF(MAX(B529,E529)>=Thresholds!$B$5,"Tier 3 - High",IF(MAX(B529,E529)>=Thresholds!$B$4,"Tier 2 - Moderate","Tier 1 - Low")) | K529: Moderate - Review | L529: Light check - Buy Box %, confirm Business Price/Quantity Discount still active, quick scan of title and main image

Sheet Thresholds
A1: Threshold Settings — edit the blue cells; the Tracker's Tier column recalculates automatically
A2: Tier | B2: B2B Sessions (lower bound) | C2: Action
A3: Tier 1 - Low | B3: < Tier 2 | C3: Low/no B2B traffic yet - set a Business Price (5-10% below retail) and Quantity Discount tiers (e.g. 5+ units 5% off, 10+ units 10% off) to attract first B2B interest; add bulk/case-pack info to title and bullets
A4: Tier 2 - Moderate | B4: 5 | C4: Light check - Buy Box %, confirm Business Price/Quantity Discount still active, quick scan of title and main image
A5: Tier 3 - High | B5: 10 | C5: Priority review - Buy Box % and stock, Business Price and Quantity Discount tiers, spec table plus bulk/case-pack info, A+ business use-case content, Business-only offers enabled, VAT invoicing support, backend B2B search terms, certifications visible
A7: Note: Tier 2 lower bound = cell B4 ; Tier 3 lower bound = cell B5. Tier 1 = below Tier 2. The Tracker's Tier column reads B4/B5 and recalculates automatically.

Sheet Summary
A1: Summary — B2B Session Drop Tracker (Amazon.de)
A3: End user | B3: Jensika (staff.users id 99)
A4: Scope | B4: Amazon.de (Germany) account only
A5: Source of record | B5: Amazon.de Seller Central Business Report export (Detail Page Sales and Traffic by Child Item), B2B columns
A6: Current window | B6: 16 Jun 2026 – 15 Jul 2026
A7: Previous window | B7: 17 May 2026 – 15 Jun 2026
A8: Total ASINs | B8: 526
A9: Tier 3 - High | B9: 4
A10: Tier 2 - Moderate | B10: 16
A11: Tier 1 - Low | B11: 506
A12: Engine | B12: Tier = MAX(prev,current) B2B Sessions vs thresholds. Session Change, Units Orders and Buy Box % are context only; they never change Tier/Status/Action.

Sheet Data Notes
A1: B2B Session Drop Tracker — Amazon.de (Germany) — REQ-21-D01
A3: Source of record: owner-supplied Amazon.de Seller Central Business Report export (Detail Page Sales and Traffic
A4: by Child Item), B2B-only columns (Sessions·Total·B2B, Page Views·Total·B2B, Units ordered·B2B). The internal
A5: database is NOT the source — its business_reports.amz_traffic_by_asin mirror is incomplete for .de B2B (May 2026
A6: missing; ~half the ASINs absent), so it cannot reproduce this report. Confirmed with the owner 2026-07-31.
A8: Included ASINs: only those with some B2B Sessions or B2B Page Views in at least one window (zero-both excluded).
A9: Tier logic: Tier = MAX(Prev, Current) B2B Sessions vs the editable Thresholds tab (Tier 2 ≥ 5, Tier 3 ≥ 10).
A10: Session Change = Current − Previous B2B Sessions (context/trend only — does NOT change Tier or Action).
A11: Units Orders and Buy Box % are context only; they never change Tier/Status/Action.
A12: Buy Box % shown for the Current window.
A14: Engine verification: all rows re-derived independently and matched the source — 0 mismatches on Session Change,
A15: Tier, Status and Action.
